demo_dec5/__init__.py
demo_dec5-0.1.0.dist-info/WHEEL
demo_dec5-0.1.0.dist-info/METADATA
demo_dec5-0.1.0.dist-info/RECORD
