Metadata-Version: 2.1
Name: demo-dec5
Version: 0.1.0
Summary: 
Author: krushna Panchvishe
Author-email: krushnap@cdac.in
Requires-Python: >=3.10,<4.0
Classifier: Programming Language :: Python :: 3
Classifier: Programming Language :: Python :: 3.10
Classifier: Programming Language :: Python :: 3.11
Requires-Dist: nano (>=0.10.0,<0.11.0)
Requires-Dist: pandas (>=1.5.2,<2.0.0)
Requires-Dist: streamlit (>=1.15.2,<2.0.0)
